superbrowser/__init__.py
superbrowser/browser.py
superbrowser/py.typed
superbrowser-0.1.1.dist-info/LICENSE
superbrowser-0.1.1.dist-info/METADATA
superbrowser-0.1.1.dist-info/WHEEL
superbrowser-0.1.1.dist-info/entry_points.txt
superbrowser-0.1.1.dist-info/top_level.txt
superbrowser-0.1.1.dist-info/RECORD
