Metadata-Version: 2.1
Name: superbrowser
Version: 0.1.1
Summary: Selenium browser with extended functionality
Author-email: Quinten Roets <qdr2104@columbia.edu>
License: MIT
Project-URL: Source Code, https://github.com/quintenroets/superbrowser
Requires-Python: >=3.10
License-File: LICENSE
Requires-Dist: selenium <5,>=4.18.1
Provides-Extra: dev
Requires-Dist: hypothesis <7,>=6.97.1 ; extra == 'dev'
Requires-Dist: package-dev-tools <1,>=0.5.11 ; extra == 'dev'
Requires-Dist: package-dev-utils <1,>=0.1.6 ; extra == 'dev'
